indexed_zstd.cpython-312-x86_64-linux-gnu.so
indexed_zstd-1.6.1.dist-info/LICENSE
indexed_zstd-1.6.1.dist-info/METADATA
indexed_zstd-1.6.1.dist-info/RECORD
indexed_zstd-1.6.1.dist-info/top_level.txt
indexed_zstd-1.6.1.dist-info/WHEEL
indexed_zstd.libs/libzstd-8d126cbb.so.1.5.5
